setup.py
dsnd_gaussian_distribution/Binomialdistribution.py
dsnd_gaussian_distribution/Gaussiandistribution.py
dsnd_gaussian_distribution/Generaldistribution.py
dsnd_gaussian_distribution/__init__.py
dsnd_gaussian_distribution.egg-info/PKG-INFO
dsnd_gaussian_distribution.egg-info/SOURCES.txt
dsnd_gaussian_distribution.egg-info/dependency_links.txt
dsnd_gaussian_distribution.egg-info/not-zip-safe
dsnd_gaussian_distribution.egg-info/top_level.txt